examples/__init__.py
examples/centralized/__init__.py
examples/centralized/main.py
examples/deploy/__init__.py
examples/deploy/complex_example/__init__.py
examples/deploy/complex_example/src/__init__.py
examples/deploy/complex_example/src/main_entry.py
examples/deploy/complex_example/src/app/__init__.py
examples/deploy/complex_example/src/app/pipe/__init__.py
examples/deploy/complex_example/src/app/pipe/constants.py
examples/deploy/complex_example/src/app/pipe/instruct_pipeline.py
examples/deploy/mnist/__init__.py
examples/deploy/mnist/src/__init__.py
examples/deploy/mnist/src/mnist_serve_main.py
examples/deploy/mnist/src/model/__init__.py
examples/deploy/mnist/src/model/mnist_model.py
examples/deploy/streaming_response/__init__.py
examples/deploy/streaming_response/src/__init__.py
examples/deploy/streaming_response/src/main_entry.py
examples/deploy/your_own_llm/__init__.py
examples/deploy/your_own_llm/src/__init__.py
examples/deploy/your_own_llm/src/main_entry.py
examples/deploy/your_own_llm/src/app/__init__.py
examples/deploy/your_own_llm/src/app/pipe/__init__.py
examples/deploy/your_own_llm/src/app/pipe/constants.py
examples/deploy/your_own_llm/src/app/pipe/instruct_pipeline.py
fedml/__init__.py
fedml/arguments.py
fedml/constants.py
fedml/launch_cross_cloud.py
fedml/launch_cross_device.py
fedml/launch_cross_silo_hi.py
fedml/launch_cross_silo_horizontal.py
fedml/launch_serving.py
fedml/launch_simulation.py
fedml/runner.py
fedml/api/__init__.py
fedml/api/api_test.py
fedml/api/constants.py
fedml/api/fedml_response.py
fedml/api/modules/__init__.py
fedml/api/modules/build.py
fedml/api/modules/cluster.py
fedml/api/modules/constants.py
fedml/api/modules/device.py
fedml/api/modules/diagnosis.py
fedml/api/modules/federate.py
fedml/api/modules/launch.py
fedml/api/modules/logs.py
fedml/api/modules/model.py
fedml/api/modules/run.py
fedml/api/modules/storage.py
fedml/api/modules/train.py
fedml/api/modules/utils.py
fedml/centralized/__init__.py
fedml-0.9.6.dist-info/LICENSE
fedml-0.9.6.dist-info/METADATA
fedml-0.9.6.dist-info/WHEEL
fedml-0.9.6.dist-info/entry_points.txt
fedml-0.9.6.dist-info/top_level.txt
fedml-0.9.6.dist-info/RECORD
