Metadata-Version: 2.2
Name: fedml
Version: 0.9.6
Summary: A research and production integrated edge-cloud library for federated/distributed machine learning at anywhere at any scale.
Home-page: https://github.com/FedML-AI/FedML
Author: FedML Team
Author-email: ch@fedml.ai
License: Apache 2.0
Keywords: distributed machine learning,federated learning,natural language processing,computer vision,Internet of Things
Classifier: Operating System :: Microsoft :: Windows
Classifier: Operating System :: POSIX
Classifier: Operating System :: Unix
Classifier: Operating System :: MacOS
Classifier: Programming Language :: Python :: 3
Classifier: Programming Language :: Python :: 3.8
Classifier: Programming Language :: Python :: 3.9
Classifier: Programming Language :: Python :: 3.10
Classifier: Programming Language :: Python :: Implementation :: CPython
Classifier: Programming Language :: Python :: Implementation :: PyPy
License-File: LICENSE
Requires-Dist: GPUtil
Requires-Dist: PyYAML
Requires-Dist: aiohttp>=3.8.1
Requires-Dist: attrdict
Requires-Dist: attrs
Requires-Dist: boto3
Requires-Dist: cachetools
Requires-Dist: chardet
Requires-Dist: click
Requires-Dist: dill
Requires-Dist: docker==6.1.3
Requires-Dist: fastapi
Requires-Dist: gensim
Requires-Dist: geventhttpclient<=2.0.9,>=1.4.4
Requires-Dist: graphviz<0.9.0,>=0.8.1
Requires-Dist: h5py
Requires-Dist: httpx
Requires-Dist: matplotlib
Requires-Dist: multiprocess
Requires-Dist: networkx<3.0
Requires-Dist: ntplib
Requires-Dist: numpy<2.0.0
Requires-Dist: onnx
Requires-Dist: paho-mqtt<2.0.0
Requires-Dist: pandas
Requires-Dist: prettytable
Requires-Dist: py-machineid
Requires-Dist: pydantic
Requires-Dist: pytest
Requires-Dist: pytest-mock
Requires-Dist: python-rapidjson>=0.9.1
Requires-Dist: redis
Requires-Dist: scikit-learn
Requires-Dist: smart-open==6.3.0
Requires-Dist: sqlalchemy
Requires-Dist: toposort
Requires-Dist: torch>=1.13.1
Requires-Dist: torchvision>=0.14.1
Requires-Dist: tqdm
Requires-Dist: tritonclient
Requires-Dist: typing_extensions
Requires-Dist: tzlocal
Requires-Dist: uvicorn
Requires-Dist: wandb==0.13.2
Requires-Dist: wget
Requires-Dist: requests<2.32
Requires-Dist: python-dotenv
Requires-Dist: protobuf<4.0dev,>=3.20.2
Requires-Dist: typer<0.10.0,>=0.3.0
Requires-Dist: fastapi-cli==0.0.1
Provides-Extra: mpi
Requires-Dist: mpi4py; extra == "mpi"
Provides-Extra: deepspeed
Requires-Dist: deepspeed>=0.10.2; extra == "deepspeed"
Provides-Extra: fhe
Requires-Dist: tenseal; extra == "fhe"
Provides-Extra: grpc
Requires-Dist: grpcio; extra == "grpc"
Provides-Extra: jax
Provides-Extra: llm
Requires-Dist: accelerate>=0.24.0; extra == "llm"
Requires-Dist: datasets>=2.14.0; extra == "llm"
Requires-Dist: einops; extra == "llm"
Requires-Dist: evaluate; extra == "llm"
Requires-Dist: ninja; extra == "llm"
Requires-Dist: packaging; extra == "llm"
Requires-Dist: peft>=0.4.0; extra == "llm"
Requires-Dist: safetensors; extra == "llm"
Requires-Dist: sentencepiece; extra == "llm"
Requires-Dist: transformers[torch]>=4.31.0; extra == "llm"
Requires-Dist: zstandard; extra == "llm"
Provides-Extra: mxnet
Requires-Dist: mxnet==2.0.0b1; extra == "mxnet"
Provides-Extra: tensorflow
Requires-Dist: tensorflow; extra == "tensorflow"
Requires-Dist: tensorflow_datasets; extra == "tensorflow"
Requires-Dist: tensorflow_federated; extra == "tensorflow"
Provides-Extra: nlp
Requires-Dist: spacy<3.3.0,>=3.2.0; extra == "nlp"
Dynamic: author
Dynamic: author-email
Dynamic: classifier
Dynamic: description
Dynamic: description-content-type
Dynamic: home-page
Dynamic: keywords
Dynamic: license
Dynamic: provides-extra
Dynamic: requires-dist
Dynamic: summary
